pdf_structify-0.1.18.dist-info/licenses/LICENSE
structify/__init__.py
structify/core/__init__.py
structify/core/base.py
structify/core/config.py
structify/core/exceptions.py
structify/extractors/__init__.py
structify/extractors/extractor.py
structify/extractors/prompt_generator.py
structify/extractors/validator.py
structify/output/__init__.py
structify/output/writers.py
structify/pipeline/__init__.py
structify/pipeline/pipeline.py
structify/preprocessing/__init__.py
structify/preprocessing/loader.py
structify/preprocessing/splitter.py
structify/progress/__init__.py
structify/progress/checkpoint.py
structify/progress/tracker.py
structify/providers/__init__.py
structify/providers/base.py
structify/providers/gemini.py
structify/schema/__init__.py
structify/schema/builder.py
structify/schema/detector.py
structify/schema/types.py
structify/state/__init__.py
structify/state/manager.py
structify/utils/__init__.py
structify/utils/json_repair.py
structify/utils/logging.py
structify/utils/retry.py
pdf_structify-0.1.18.dist-info/METADATA
pdf_structify-0.1.18.dist-info/WHEEL
pdf_structify-0.1.18.dist-info/top_level.txt
pdf_structify-0.1.18.dist-info/RECORD
