Metadata-Version: 2.4
Name: pdf-structify
Version: 0.1.18
Summary: Extract structured data from PDFs using LLMs with sklearn-like API
Author: Ahmed Dawood
License-Expression: MIT
Project-URL: Homepage, https://github.com/Economist-Ahmed-Dawoud/pdf-structify
Project-URL: Documentation, https://github.com/Economist-Ahmed-Dawoud/pdf-structify#readme
Project-URL: Repository, https://github.com/Economist-Ahmed-Dawoud/pdf-structify
Project-URL: Issues, https://github.com/Economist-Ahmed-Dawoud/pdf-structify/issues
Keywords: pdf,extraction,llm,gemini,structured-data,machine-learning,data-extraction,document-processing
Classifier: Development Status :: 3 - Alpha
Classifier: Intended Audience :: Developers
Classifier: Intended Audience :: Science/Research
Classifier: Programming Language :: Python :: 3
Classifier: Programming Language :: Python :: 3.10
Classifier: Programming Language :: Python :: 3.11
Classifier: Programming Language :: Python :: 3.12
Classifier: Topic :: Scientific/Engineering :: Artificial Intelligence
Classifier: Topic :: Text Processing :: General
Requires-Python: >=3.10
License-File: LICENSE
Requires-Dist: google-genai>=1.0.0
Requires-Dist: pypdf>=4.0.0
Requires-Dist: rich>=13.0.0
Requires-Dist: pydantic>=2.0.0
Requires-Dist: python-dotenv>=1.0.0
Requires-Dist: pyyaml>=6.0.0
Requires-Dist: pandas>=2.0.0
Provides-Extra: dev
Requires-Dist: pytest>=7.0.0; extra == "dev"
Requires-Dist: pytest-cov>=4.0.0; extra == "dev"
Requires-Dist: black>=23.0.0; extra == "dev"
Requires-Dist: ruff>=0.1.0; extra == "dev"
Dynamic: license-file
